{
    "Imgur": {
        "Url": "https://api.imgur.com/3/",
        "RefreshToken": "57fdf8a2495ed27476b3e79cb94c35ee4335cb08",
        "ClientSecret": "ccd93164c3ec017ae2d3aade718bd52608bbb2dc",
        "ClientId": "f7e7079b7a8d860",
        "AccessToken": "b906d2ab0e55537861e1d05770f10135ab8816b8"
    },
    "Google": {
        "ClientSecret": "P1zLdaso_y8CWJV1AfvNglTU",
        "ClientId": "f7e7079b7a8d860"
    },
    "Facebook": {
        "AppSecret": "286a115ab79c1541b6378f75b04c62fe",
        "AppId": "790564174746229"
    }
}